async_fifo.v
`timescale 1ns/1ps

module async_fifo #(
    parameter DATA_WIDTH = 8,
    parameter DEPTH = 16
)(
    input  wire                  wr_clk,
    input  wire                  rd_clk,
    input  wire                  arst_n,

    input  wire                  wr_en,
    input  wire [DATA_WIDTH-1:0] wr_data,

    input  wire                  rd_en,
    output reg  [DATA_WIDTH-1:0] rd_data,

    input  wire [4:0]            afull_threshold,
    input  wire [4:0]            aempty_threshold,

    output reg                   full,
    output reg                   empty,
    output reg                   afull,
    output reg                   aempty
);

    // =========================================================
    // PARAMETERS
    // =========================================================

    localparam ADDR_WIDTH = $clog2(DEPTH);
    localparam PTR_WIDTH  = ADDR_WIDTH + 1;

    // =========================================================
    // FIFO MEMORY
    // =========================================================

    reg [DATA_WIDTH-1:0] mem [0:DEPTH-1];

    // =========================================================
    // WRITE POINTER
    // =========================================================

    reg [PTR_WIDTH-1:0] wr_bin;
    reg [PTR_WIDTH-1:0] wr_gray;

    reg [PTR_WIDTH-1:0] wr_bin_next;
    reg [PTR_WIDTH-1:0] wr_gray_next;

    wire write_do;

    assign write_do = wr_en && !full;

    always @(*) begin

        wr_bin_next = wr_bin + write_do;

        wr_gray_next =
            wr_bin_next ^ (wr_bin_next >> 1);

    end

    // =========================================================
    // READ POINTER
    // =========================================================

    reg [PTR_WIDTH-1:0] rd_bin;
    reg [PTR_WIDTH-1:0] rd_gray;

    reg [PTR_WIDTH-1:0] rd_bin_next;
    reg [PTR_WIDTH-1:0] rd_gray_next;

    wire read_do;

    assign read_do = rd_en && !empty;

    always @(*) begin

        rd_bin_next = rd_bin + read_do;

        rd_gray_next =
            rd_bin_next ^ (rd_bin_next >> 1);

    end

    // =========================================================
    // READ POINTER SYNCHRONIZER
    // READ DOMAIN -> WRITE DOMAIN
    // =========================================================

    reg [PTR_WIDTH-1:0] rd_gray_sync1;
    reg [PTR_WIDTH-1:0] rd_gray_sync2;

    always @(posedge wr_clk or negedge arst_n) begin

        if (!arst_n) begin

            rd_gray_sync1 <= {PTR_WIDTH{1'b0}};
            rd_gray_sync2 <= {PTR_WIDTH{1'b0}};

        end
        else begin

            rd_gray_sync1 <= rd_gray;
            rd_gray_sync2 <= rd_gray_sync1;

        end

    end

    // =========================================================
    // WRITE POINTER SYNCHRONIZER
    // WRITE DOMAIN -> READ DOMAIN
    // =========================================================

    reg [PTR_WIDTH-1:0] wr_gray_sync1;
    reg [PTR_WIDTH-1:0] wr_gray_sync2;

    always @(posedge rd_clk or negedge arst_n) begin

        if (!arst_n) begin

            wr_gray_sync1 <= {PTR_WIDTH{1'b0}};
            wr_gray_sync2 <= {PTR_WIDTH{1'b0}};

        end
        else begin

            wr_gray_sync1 <= wr_gray;
            wr_gray_sync2 <= wr_gray_sync1;

        end

    end

    // =========================================================
    // GRAY -> BINARY FUNCTION
    // =========================================================

    function [PTR_WIDTH-1:0] gray_to_binary;

        input [PTR_WIDTH-1:0] gray;

        integer i;

        begin

            gray_to_binary[PTR_WIDTH-1] =
                gray[PTR_WIDTH-1];

            for (i = PTR_WIDTH-2; i >= 0; i = i - 1) begin

                gray_to_binary[i] =
                    gray_to_binary[i+1] ^ gray[i];

            end

        end

    endfunction

    // =========================================================
    // SYNCHRONIZED POINTERS IN BINARY
    // =========================================================

    wire [PTR_WIDTH-1:0] rd_bin_sync;
    wire [PTR_WIDTH-1:0] wr_bin_sync;

    assign rd_bin_sync =
        gray_to_binary(rd_gray_sync2);

    assign wr_bin_sync =
        gray_to_binary(wr_gray_sync2);

    // =========================================================
    // FULL DETECTION
    // =========================================================

    wire [PTR_WIDTH-1:0] full_compare;

    assign full_compare =
        rd_gray_sync2 ^
        ((1 << (PTR_WIDTH-1)) |
         (1 << (PTR_WIDTH-2)));

    wire full_next;

    assign full_next =
        (wr_gray_next == full_compare);

    // =========================================================
    // EMPTY DETECTION
    // =========================================================

    wire empty_next;

    assign empty_next =
        (rd_gray_next == wr_gray_sync2);

    // =========================================================
    // FIFO OCCUPANCY
    // =========================================================

    wire [PTR_WIDTH-1:0] write_count;
    wire [PTR_WIDTH-1:0] read_count;

    assign write_count =
        wr_bin - rd_bin_sync;

    assign read_count =
        wr_bin_sync - rd_bin;

    // =========================================================
    // ALMOST FULL
    // =========================================================

    wire afull_next;

    assign afull_next =
        (write_count >= afull_threshold);

    // =========================================================
    // ALMOST EMPTY
    // =========================================================

    wire aempty_next;

    assign aempty_next =
        (read_count <= aempty_threshold);

    // =========================================================
    // WRITE POINTER + FULL + AFULL
    // =========================================================

    always @(posedge wr_clk or negedge arst_n) begin

        if (!arst_n) begin

            wr_bin <= {PTR_WIDTH{1'b0}};
            wr_gray <= {PTR_WIDTH{1'b0}};

            full <= 1'b0;
            afull <= 1'b0;

        end
        else begin

            wr_bin <= wr_bin_next;
            wr_gray <= wr_gray_next;

            full <= full_next;
            afull <= afull_next;

        end

    end

    // =========================================================
    // READ POINTER + EMPTY + AEMPTY
    // =========================================================

    always @(posedge rd_clk or negedge arst_n) begin

        if (!arst_n) begin

            rd_bin <= {PTR_WIDTH{1'b0}};
            rd_gray <= {PTR_WIDTH{1'b0}};

            empty <= 1'b1;
            aempty <= 1'b1;

            rd_data <= {DATA_WIDTH{1'b0}};

        end
        else begin

            rd_bin <= rd_bin_next;
            rd_gray <= rd_gray_next;

            empty <= empty_next;
            aempty <= aempty_next;

        end

    end

    // =========================================================
    // MEMORY WRITE
    // =========================================================

    always @(posedge wr_clk) begin

        if (write_do)

            mem[wr_bin[ADDR_WIDTH-1:0]] <= wr_data;

    end

    // =========================================================
    // MEMORY READ
    // =========================================================

    always @(posedge rd_clk) begin

        if (read_do)

            rd_data <= mem[rd_bin[ADDR_WIDTH-1:0]];

    end

endmodule

tb_async_fifo.v
`timescale 1ns/1ps

module tb_async_fifo;

    // =========================================================
    // PARAMETERS
    // =========================================================

    parameter DATA_WIDTH = 8;
    parameter DEPTH = 16;

    // =========================================================
    // CLOCKS
    // =========================================================

    reg wr_clk;
    reg rd_clk;

    // =========================================================
    // RESET
    // =========================================================

    reg arst_n;

    // =========================================================
    // WRITE SIGNALS
    // =========================================================

    reg                  wr_en;
    reg [DATA_WIDTH-1:0] wr_data;

    // =========================================================
    // READ SIGNALS
    // =========================================================

    reg                  rd_en;
    wire [DATA_WIDTH-1:0] rd_data;

    // =========================================================
    // WATERMARK THRESHOLDS
    // =========================================================

    reg [4:0] afull_threshold;
    reg [4:0] aempty_threshold;

    // =========================================================
    // FIFO FLAGS
    // =========================================================

    wire full;
    wire empty;
    wire afull;
    wire aempty;

    // =========================================================
    // DUT
    // =========================================================

    async_fifo #(
        .DATA_WIDTH(DATA_WIDTH),
        .DEPTH(DEPTH)
    ) dut (

        .wr_clk(wr_clk),
        .rd_clk(rd_clk),
        .arst_n(arst_n),

        .wr_en(wr_en),
        .wr_data(wr_data),

        .rd_en(rd_en),
        .rd_data(rd_data),

        .afull_threshold(afull_threshold),
        .aempty_threshold(aempty_threshold),

        .full(full),
        .empty(empty),
        .afull(afull),
        .aempty(aempty)

    );

    // =========================================================
    // WRITE CLOCK
    // 10 ns PERIOD
    // =========================================================

    initial begin

        wr_clk = 1'b0;

        forever
            #5 wr_clk = ~wr_clk;

    end

    // =========================================================
    // READ CLOCK
    // 14 ns PERIOD
    // =========================================================

    initial begin

        rd_clk = 1'b0;

        forever
            #7 rd_clk = ~rd_clk;

    end

    // =========================================================
    // VCD WAVEFORM
    // =========================================================

    
    initial begin

    $dumpfile("async_fifo.vcd");

    // Dump complete testbench hierarchy
    $dumpvars(0, tb_async_fifo);

    // Explicitly dump FIFO DUT hierarchy
    $dumpvars(0, tb_async_fifo.dut);

    end
    // =========================================================
    // MAIN TEST
    // =========================================================

    initial begin

        // -----------------------------------------------------
        // INITIAL CONDITIONS
        // -----------------------------------------------------

        arst_n = 1'b0;

        wr_en = 1'b0;
        wr_data = 8'h00;

        rd_en = 1'b0;

        // -----------------------------------------------------
        // WATERMARK CONFIGURATION
        // -----------------------------------------------------

        afull_threshold = 12;

        aempty_threshold = 2;

        // -----------------------------------------------------
        // RESET
        // -----------------------------------------------------

        #25;

        arst_n = 1'b1;

        $display("");
        $display("========================================");
        $display(" RESET RELEASED ");
        $display("========================================");
        $display("");

        // Wait for FIFO to become ready

        #30;

        // -----------------------------------------------------
        // WRITE DATA
        // -----------------------------------------------------

        write_data(8'hA1);
        write_data(8'hA2);
        write_data(8'hA3);
        write_data(8'hA4);
        write_data(8'hA5);
        write_data(8'hA6);
        write_data(8'hA7);
        write_data(8'hA8);

        // -----------------------------------------------------
        // WAIT FOR CDC
        // -----------------------------------------------------

        #60;

        // -----------------------------------------------------
        // READ DATA
        // -----------------------------------------------------

        read_data;
        read_data;
        read_data;
        read_data;

        // -----------------------------------------------------
        // WRITE MORE DATA
        // -----------------------------------------------------

        write_data(8'hB1);
        write_data(8'hB2);
        write_data(8'hB3);
        write_data(8'hB4);

        // -----------------------------------------------------
        // WAIT
        // -----------------------------------------------------

        #60;

        // -----------------------------------------------------
        // READ MORE DATA
        // -----------------------------------------------------

        read_data;
        read_data;
        read_data;
        read_data;
        read_data;
        read_data;
        read_data;
        read_data;

        // -----------------------------------------------------
        // FINAL WAIT
        // -----------------------------------------------------

        #100;

        $display("");
        $display("========================================");
        $display(" PS-04 ASYNC FIFO TEST COMPLETE ");
        $display("========================================");
        $display("");

        $finish;

    end

    // =========================================================
    // WRITE TASK
    // =========================================================

    task write_data;

        input [DATA_WIDTH-1:0] data;

        begin

            @(posedge wr_clk);

            if (!full) begin

                wr_en = 1'b1;

                wr_data = data;

                $display(
                    "%0t : WRITE DATA = %h",
                    $time,
                    data
                );

            end

            else begin

                wr_en = 1'b0;

                $display(
                    "%0t : WRITE BLOCKED - FIFO FULL",
                    $time
                );

            end

            @(posedge wr_clk);

            wr_en = 1'b0;

        end

    endtask

    // =========================================================
    // READ TASK
    // =========================================================

    task read_data;

        begin

            @(posedge rd_clk);

            if (!empty) begin

                rd_en = 1'b1;

                $display(
                    "%0t : READ REQUEST",
                    $time
                );

            end

            else begin

                rd_en = 1'b0;

                $display(
                    "%0t : READ BLOCKED - FIFO EMPTY",
                    $time
                );

            end

            @(posedge rd_clk);

            rd_en = 1'b0;

        end

    endtask

    // =========================================================
    // WRITE DOMAIN MONITOR
    // =========================================================

    always @(posedge wr_clk) begin

        $display(
            "%0t : WR | BIN=%0d GRAY=%b FULL=%b AFULL=%b",
            $time,
            dut.wr_bin,
            dut.wr_gray,
            full,
            afull
        );

    end

    // =========================================================
    // READ DOMAIN MONITOR
    // =========================================================

    always @(posedge rd_clk) begin

        $display(
            "%0t : RD | BIN=%0d GRAY=%b EMPTY=%b AEMPTY=%b DATA=%h",
            $time,
            dut.rd_bin,
            dut.rd_gray,
            empty,
            aempty,
            rd_data
        );

    end

endmodule

async_fifo.vcd
$date
	Fri Aug 28 07:07:33 2026
$end
$version
	Icarus Verilog
$end
$timescale
	1ps
$end
$scope module tb_async_fifo $end
$var wire 8 ! rd_data [7:0] $end
$var wire 1 " full $end
$var wire 1 # empty $end
$var wire 1 $ afull $end
$var wire 1 % aempty $end
$var parameter 32 & DATA_WIDTH $end
$var parameter 32 ' DEPTH $end
$var reg 5 ( aempty_threshold [4:0] $end
$var reg 5 ) afull_threshold [4:0] $end
$var reg 1 * arst_n $end
$var reg 1 + rd_clk $end
$var reg 1 , rd_en $end
$var reg 1 - wr_clk $end
$var reg 8 . wr_data [7:0] $end
$var reg 1 / wr_en $end
$scope module dut $end
$var wire 5 0 aempty_threshold [4:0] $end
$var wire 5 1 afull_threshold [4:0] $end
$var wire 1 * arst_n $end
$var wire 5 2 full_compare [4:0] $end
$var wire 1 + rd_clk $end
$var wire 1 , rd_en $end
$var wire 1 3 read_do $end
$var wire 1 - wr_clk $end
$var wire 8 4 wr_data [7:0] $end
$var wire 1 / wr_en $end
$var wire 1 5 write_do $end
$var wire 5 6 write_count [4:0] $end
$var wire 5 7 wr_bin_sync [4:0] $end
$var wire 5 8 read_count [4:0] $end
$var wire 5 9 rd_bin_sync [4:0] $end
$var wire 1 : full_next $end
$var wire 1 ; empty_next $end
$var wire 1 < afull_next $end
$var wire 1 = aempty_next $end
$var parameter 32 > ADDR_WIDTH $end
$var parameter 32 ? DATA_WIDTH $end
$var parameter 32 @ DEPTH $end
$var parameter 33 A PTR_WIDTH $end
$var reg 1 % aempty $end
$var reg 1 $ afull $end
$var reg 1 # empty $end
$var reg 1 " full $end
$var reg 5 B rd_bin [4:0] $end
$var reg 5 C rd_bin_next [4:0] $end
$var reg 8 D rd_data [7:0] $end
$var reg 5 E rd_gray [4:0] $end
$var reg 5 F rd_gray_next [4:0] $end
$var reg 5 G rd_gray_sync1 [4:0] $end
$var reg 5 H rd_gray_sync2 [4:0] $end
$var reg 5 I wr_bin [4:0] $end
$var reg 5 J wr_bin_next [4:0] $end
$var reg 5 K wr_gray [4:0] $end
$var reg 5 L wr_gray_next [4:0] $end
$var reg 5 M wr_gray_sync1 [4:0] $end
$var reg 5 N wr_gray_sync2 [4:0] $end
$scope function gray_to_binary $end
$var reg 5 O gray [4:0] $end
$var integer 32 P i [31:0] $end
$upscope $end
$upscope $end
$scope task read_data $end
$upscope $end
$scope task write_data $end
$var reg 8 Q data [7:0] $end
$upscope $end
$upscope $end
$scope module tb_async_fifo $end
$scope module dut $end
$scope function gray_to_binary $end
$upscope $end
$upscope $end
$upscope $end
$enddefinitions $end
$comment Show the parameter values. $end
$dumpall
b101 A
b10000 @
b1000 ?
b100 >
b10000 '
b1000 &
$end
#0
$dumpvars
bx Q
b11111111111111111111111111111111 P
b0 O
b0 N
b0 M
b0 L
b0 K
b0 J
b0 I
b0 H
b0 G
b0 F
b0 E
b0 D
b0 C
b0 B
1=
0<
1;
0:
b0 9
b0 8
b0 7
b0 6
05
b0 4
03
b11000 2
b1100 1
b10 0
0/
b0 .
0-
0,
0+
0*
b1100 )
b10 (
1%
0$
1#
0"
b0 !
$end
#5000
1-
#7000
1+
#10000
0-
#14000
0+
#15000
1-
#20000
0-
#21000
1+
#25000
1-
1*
#28000
0+
#30000
0-
#35000
1-
1+
#40000
0-
#42000
0+
#45000
1-
#49000
1+
#50000
0-
#55000
b1 L
b1 J
15
b10100001 .
b10100001 4
1/
1-
b10100001 Q
#56000
0+
#60000
0-
#63000
1+
#65000
b1 K
b1 6
b1 I
b1 L
b1 J
05
b10100010 Q
0/
1-
#70000
0-
0+
#75000
b11 L
b10 J
15
b10100010 .
b10100010 4
1/
1-
#77000
b1 M
1+
#80000
0-
#84000
0+
#85000
b11 K
b10 6
b10 I
b11 L
b10 J
05
b10100011 Q
0/
1-
#90000
0-
#91000
b1 8
b1 7
b11111111111111111111111111111111 P
b1 O
0;
b1 N
b11 M
1+
#95000
b10 L
b11 J
15
b10100011 .
b10100011 4
1/
1-
#98000
0+
#100000
0-
#105000
b10 8
b10 7
b11111111111111111111111111111111 P
b11 O
b10 K
b11 6
b11 I
b11 N
0#
b10 L
b11 J
05
b10100100 Q
0/
1-
1+
#110000
0-
#112000
0+
#115000
b110 L
b100 J
15
b10100100 .
b10100100 4
1/
1-
#119000
b10 M
1+
#120000
0-
#125000
b110 K
b100 6
b100 I
b110 L
b100 J
05
b10100101 Q
0/
1-
#126000
0+
#130000
0-
#133000
0=
b11 8
b11 7
b11111111111111111111111111111111 P
b10 O
b10 N
b110 M
1+
#135000
b111 L
b101 J
15
b10100101 .
b10100101 4
1/
1-
#140000
0-
0+
#145000
b111 K
b101 6
b101 I
b111 L
b101 J
05
b10100110 Q
0/
1-
#147000
b100 8
b100 7
b11111111111111111111111111111111 P
b110 O
0%
b110 N
b111 M
1+
#150000
0-
#154000
0+
#155000
b101 L
b110 J
15
b10100110 .
b10100110 4
1/
1-
#160000
0-
#161000
b101 8
b101 7
b11111111111111111111111111111111 P
b111 O
b111 N
1+
#165000
b101 K
b110 6
b110 I
b101 L
b110 J
05
b10100111 Q
0/
1-
#168000
0+
#170000
0-
#175000
b101 M
b100 L
b111 J
15
b10100111 .
b10100111 4
1/
1-
1+
#180000
0-
#182000
0+
#185000
b100 K
b111 6
b111 I
b100 L
b111 J
05
b10101000 Q
0/
1-
#189000
b110 8
b110 7
b11111111111111111111111111111111 P
b101 O
b101 N
b100 M
1+
#190000
0-
#195000
b1100 L
b1000 J
15
b10101000 .
b10101000 4
1/
1-
#196000
0+
#200000
0-
#203000
b111 8
b111 7
b11111111111111111111111111111111 P
b100 O
b100 N
1+
#205000
b1100 K
b1000 6
b1000 I
b1100 L
b1000 J
05
0/
1-
#210000
0-
0+
#215000
1-
#217000
b1100 M
1+
#220000
0-
#224000
0+
#225000
1-
#230000
0-
#231000
b1000 8
b1000 7
b11111111111111111111111111111111 P
b1100 O
b1100 N
1+
#235000
1-
#238000
0+
#240000
0-
#245000
1-
1+
#250000
0-
#252000
0+
#255000
1-
#259000
1+
#260000
0-
#265000
1-
#266000
0+
#270000
0-
#273000
b1 F
b1 C
13
1,
1+
#275000
1-
#280000
0-
0+
#285000
1-
#287000
b10100001 !
b10100001 D
b1 E
b111 8
b1 B
b1 F
b1 C
03
0,
1+
#290000
0-
#294000
0+
#295000
b1 G
1-
#300000
0-
#301000
b11 F
b10 C
13
1,
1+
#305000
b111 6
b1 9
b11111111111111111111111111111111 P
b1 O
b11001 2
b1 H
1-
#308000
0+
#310000
0-
#315000
b10100010 !
b10100010 D
b11 E
b110 8
b10 B
b11 F
b10 C
03
0,
1-
1+
#320000
0-
#322000
0+
#325000
b11 G
1-
#329000
b10 F
b11 C
13
1,
1+
#330000
0-
#335000
b110 6
b10 9
b11111111111111111111111111111111 P
b11 O
b11011 2
b11 H
1-
#336000
0+
#340000
0-
#343000
b10100011 !
b10100011 D
b10 E
b101 8
b11 B
b10 F
b11 C
03
0,
1+
#345000
b10 G
1-
#350000
0-
0+
#355000
b101 6
b11 9
b11111111111111111111111111111111 P
b10 O
b11010 2
b10 H
1-
#357000
b110 F
b100 C
13
1,
1+
#360000
0-
#364000
0+
#365000
1-
#370000
0-
#371000
b10100100 !
b10100100 D
b110 E
b100 8
b100 B
b110 F
b100 C
03
b10110001 Q
0,
1+
#375000
b110 G
b1101 L
b1001 J
15
b10110001 .
b10110001 4
1/
1-
#378000
0+
#380000
0-
#385000
b100 9
b11111111111111111111111111111111 P
b110 O
b11110 2
b1101 K
b101 6
b1001 I
b110 H
b1101 L
b1001 J
05
b10110010 Q
0/
1-
1+
#390000
0-
#392000
0+
#395000
b1111 L
b1010 J
15
b10110010 .
b10110010 4
1/
1-
#399000
b1101 M
1+
#400000
0-
#405000
b1111 K
b110 6
b1010 I
b1111 L
b1010 J
05
b10110011 Q
0/
1-
#406000
0+
#410000
0-
#413000
b101 8
b1001 7
b11111111111111111111111111111111 P
b1101 O
b1101 N
b1111 M
1+
#415000
b1110 L
b1011 J
15
b10110011 .
b10110011 4
1/
1-
#420000
0-
0+
#425000
b1110 K
b111 6
b1011 I
b1110 L
b1011 J
05
b10110100 Q
0/
1-
#427000
b110 8
b1010 7
b11111111111111111111111111111111 P
b1111 O
b1111 N
b1110 M
1+
#430000
0-
#434000
0+
#435000
b1010 L
b1100 J
15
b10110100 .
b10110100 4
1/
1-
#440000
0-
#441000
b111 8
b1011 7
b11111111111111111111111111111111 P
b1110 O
b1110 N
1+
#445000
b1010 K
b1000 6
b1100 I
b1010 L
b1100 J
05
0/
1-
#448000
0+
#450000
0-
#455000
b1010 M
1-
1+
#460000
0-
#462000
0+
#465000
1-
#469000
b1000 8
b1100 7
b11111111111111111111111111111111 P
b1010 O
b1010 N
1+
#470000
0-
#475000
1-
#476000
0+
#480000
0-
#483000
1+
#485000
1-
#490000
0-
0+
#495000
1-
#497000
1+
#500000
0-
#504000
0+
#505000
1-
#510000
0-
#511000
b111 F
b101 C
13
1,
1+
#515000
1-
#518000
0+
#520000
0-
#525000
b10100101 !
b10100101 D
b111 E
b111 8
b101 B
b111 F
b101 C
03
0,
1-
1+
#530000
0-
#532000
0+
#535000
b111 G
1-
#539000
b101 F
b110 C
13
1,
1+
#540000
0-
#545000
b111 6
b101 9
b11111111111111111111111111111111 P
b111 O
b11111 2
b111 H
1-
#546000
0+
#550000
0-
#553000
b10100110 !
b10100110 D
b101 E
b110 8
b110 B
b101 F
b110 C
03
0,
1+
#555000
b101 G
1-
#560000
0-
0+
#565000
b110 6
b110 9
b11111111111111111111111111111111 P
b101 O
b11101 2
b101 H
1-
#567000
b100 F
b111 C
13
1,
1+
#570000
0-
#574000
0+
#575000
1-
#580000
0-
#581000
b10100111 !
b10100111 D
b100 E
b101 8
b111 B
b100 F
b111 C
03
0,
1+
#585000
b100 G
1-
#588000
0+
#590000
0-
#595000
b101 6
b111 9
b11111111111111111111111111111111 P
b100 O
b11100 2
b100 H
b1100 F
b1000 C
13
1,
1-
1+
#600000
0-
#602000
0+
#605000
1-
#609000
b10101000 !
b10101000 D
b1100 E
b100 8
b1000 B
b1100 F
b1000 C
03
0,
1+
#610000
0-
#615000
b1100 G
1-
#616000
0+
#620000
0-
#623000
b1101 F
b1001 C
13
1,
1+
#625000
b100 6
b1000 9
b11111111111111111111111111111111 P
b1100 O
b10100 2
b1100 H
1-
#630000
0-
0+
#635000
1-
#637000
b10110001 !
b10110001 D
b1101 E
b11 8
b1001 B
b1101 F
b1001 C
03
0,
1+
#640000
0-
#644000
0+
#645000
b1101 G
1-
#650000
0-
#651000
b1111 F
b1010 C
13
1,
1+
#655000
b11 6
b1001 9
b11111111111111111111111111111111 P
b1101 O
b10101 2
b1101 H
1-
#658000
0+
#660000
0-
#665000
b10110010 !
b10110010 D
b1111 E
1=
b10 8
b1010 B
b1111 F
b1010 C
03
0,
1-
1+
#670000
0-
#672000
0+
#675000
b1111 G
1-
#679000
1%
b1110 F
b1011 C
13
1,
1+
#680000
0-
#685000
b10 6
b1010 9
b11111111111111111111111111111111 P
b1111 O
b10111 2
b1111 H
1-
#686000
0+
#690000
0-
#693000
b10110011 !
b10110011 D
b1110 E
b1 8
b1011 B
b1110 F
b1011 C
03
0,
1+
#695000
b1110 G
1-
#700000
0-
0+
#705000
b1 6
b1011 9
b11111111111111111111111111111111 P
b1110 O
b10110 2
b1110 H
1-
#707000
1;
b1010 F
b1100 C
13
1,
1+
#710000
0-
#714000
0+
#715000
1-
#720000
0-
#721000
b10110100 !
b10110100 D
1#
b1010 E
b0 8
b1100 B
1;
b1010 F
b1100 C
03
0,
1+
#725000
b1010 G
1-
#728000
0+
#730000
0-
#735000
b0 6
b1100 9
b11111111111111111111111111111111 P
b1010 O
b10010 2
b1010 H
1-
1+
