src/tb_async_fifo_backup.v
`timescale 1ns/1ps

module async_fifo #(
    parameter DATA_WIDTH = 8,
    parameter DEPTH      = 16
)(
    input  wire                  wr_clk,
    input  wire                  rd_clk,
    input  wire                  arst_n,

    input  wire                  wr_en,
    input  wire [DATA_WIDTH-1:0] wr_data,

    input  wire                  rd_en,
    output reg  [DATA_WIDTH-1:0] rd_data,

    input  wire [4:0]            afull_threshold,
    input  wire [4:0]            aempty_threshold,

    output reg                   full,
    output reg                   empty,
    output reg                   afull,
    output reg                   aempty
);

    // =========================================================
    // PARAMETERS
    // =========================================================

    localparam ADDR_WIDTH = $clog2(DEPTH);
    localparam PTR_WIDTH  = ADDR_WIDTH + 1;

    // =========================================================
    // FIFO MEMORY
    // =========================================================

    reg [DATA_WIDTH-1:0] mem [0:DEPTH-1];

    // =========================================================
    // WRITE POINTER
    // =========================================================

    reg [PTR_WIDTH-1:0] wr_bin;
    reg [PTR_WIDTH-1:0] wr_gray;

    reg [PTR_WIDTH-1:0] wr_bin_next;
    reg [PTR_WIDTH-1:0] wr_gray_next;

    wire write_do;

    assign write_do = wr_en && !full;

    // Binary and Gray-code next-state logic
    always @(*) begin

        wr_bin_next = wr_bin + write_do;

        wr_gray_next =
            wr_bin_next ^ (wr_bin_next >> 1);

    end

    // =========================================================
    // READ POINTER
    // =========================================================

    reg [PTR_WIDTH-1:0] rd_bin;
    reg [PTR_WIDTH-1:0] rd_gray;

    reg [PTR_WIDTH-1:0] rd_bin_next;
    reg [PTR_WIDTH-1:0] rd_gray_next;

    wire read_do;

    assign read_do = rd_en && !empty;

    // Binary and Gray-code next-state logic
    always @(*) begin

        rd_bin_next = rd_bin + read_do;

        rd_gray_next =
            rd_bin_next ^ (rd_bin_next >> 1);

    end

    // =========================================================
    // READ POINTER SYNCHRONIZER
    // READ DOMAIN -> WRITE DOMAIN
    //
    // Two flip-flops reduce metastability propagation.
    // =========================================================

    reg [PTR_WIDTH-1:0] rd_gray_sync1;
    reg [PTR_WIDTH-1:0] rd_gray_sync2;

    always @(posedge wr_clk or negedge arst_n) begin

        if (!arst_n) begin

            rd_gray_sync1 <= {PTR_WIDTH{1'b0}};
            rd_gray_sync2 <= {PTR_WIDTH{1'b0}};

        end
        else begin

            rd_gray_sync1 <= rd_gray;
            rd_gray_sync2 <= rd_gray_sync1;

        end

    end

    // =========================================================
    // WRITE POINTER SYNCHRONIZER
    // WRITE DOMAIN -> READ DOMAIN
    //
    // Two flip-flops reduce metastability propagation.
    // =========================================================

    reg [PTR_WIDTH-1:0] wr_gray_sync1;
    reg [PTR_WIDTH-1:0] wr_gray_sync2;

    always @(posedge rd_clk or negedge arst_n) begin

        if (!arst_n) begin

            wr_gray_sync1 <= {PTR_WIDTH{1'b0}};
            wr_gray_sync2 <= {PTR_WIDTH{1'b0}};

        end
        else begin

            wr_gray_sync1 <= wr_gray;
            wr_gray_sync2 <= wr_gray_sync1;

        end

    end

    // =========================================================
    // GRAY -> BINARY FUNCTION
    // =========================================================

    function [PTR_WIDTH-1:0] gray_to_binary;

        input [PTR_WIDTH-1:0] gray;

        integer i;

        begin

            gray_to_binary[PTR_WIDTH-1] =
                gray[PTR_WIDTH-1];

            for (i = PTR_WIDTH-2; i >= 0; i = i - 1) begin

                gray_to_binary[i] =
                    gray_to_binary[i+1] ^ gray[i];

            end

        end

    endfunction

    // =========================================================
    // SYNCHRONIZED POINTERS IN BINARY
    // =========================================================

    wire [PTR_WIDTH-1:0] rd_bin_sync;
    wire [PTR_WIDTH-1:0] wr_bin_sync;

    assign rd_bin_sync =
        gray_to_binary(rd_gray_sync2);

    assign wr_bin_sync =
        gray_to_binary(wr_gray_sync2);

    // =========================================================
    // FULL DETECTION
    //
    // FIFO is full when the next write Gray pointer equals
    // the synchronized read pointer with the two MSBs inverted.
    //
    // For DEPTH = 16:
    // PTR_WIDTH = 5
    //
    // =========================================================

    wire [PTR_WIDTH-1:0] full_compare;

    assign full_compare = {
        ~rd_gray_sync2[PTR_WIDTH-1:
                       PTR_WIDTH-2],
         rd_gray_sync2[PTR_WIDTH-3:0]
    };

    wire full_next;

    assign full_next =
        (wr_gray_next == full_compare);

    // =========================================================
    // EMPTY DETECTION
    //
    // FIFO is empty when the next read Gray pointer equals
    // the synchronized write Gray pointer.
    // =========================================================

    wire empty_next;

    assign empty_next =
        (rd_gray_next == wr_gray_sync2);

    // =========================================================
    // FIFO OCCUPANCY
    //
    // These counts are local-domain estimates based on the
    // synchronized pointer from the opposite clock domain.
    // =========================================================

    wire [PTR_WIDTH-1:0] write_count;
    wire [PTR_WIDTH-1:0] read_count;

    assign write_count =
        wr_bin - rd_bin_sync;

    assign read_count =
        wr_bin_sync - rd_bin;

    // =========================================================
    // ALMOST FULL
    //
    // Current implementation:
    // AFULL becomes active when occupancy reaches or exceeds
    // the programmed threshold.
    //
    // Example:
    // threshold = 12
    // occupancy >= 12 -> AFULL = 1
    //
    // =========================================================

    wire afull_next;

    assign afull_next =
        (write_count >= afull_threshold);

    // =========================================================
    // ALMOST EMPTY
    //
    // AEMPTY becomes active when the number of stored entries
    // is less than or equal to the programmed threshold.
    //
    // Example:
    // threshold = 2
    // occupancy <= 2 -> AEMPTY = 1
    //
    // =========================================================

    wire aempty_next;

    assign aempty_next =
        (read_count <= aempty_threshold);

    // =========================================================
    // WRITE DOMAIN
    //
    // Updates:
    //   - write binary pointer
    //   - write Gray pointer
    //   - FULL flag
    //   - AFULL flag
    // =========================================================

    always @(posedge wr_clk or negedge arst_n) begin

        if (!arst_n) begin

            wr_bin  <= {PTR_WIDTH{1'b0}};
            wr_gray <= {PTR_WIDTH{1'b0}};

            full  <= 1'b0;
            afull <= 1'b0;

        end
        else begin

            wr_bin  <= wr_bin_next;
            wr_gray <= wr_gray_next;

            full  <= full_next;
            afull <= afull_next;

        end

    end

    // =========================================================
    // READ DOMAIN
    //
    // IMPORTANT:
    // rd_data is assigned ONLY HERE.
    //
    // This eliminates the previous Yosys multiple-driver
    // warning.
    // =========================================================

    always @(posedge rd_clk or negedge arst_n) begin

        if (!arst_n) begin

            rd_bin  <= {PTR_WIDTH{1'b0}};
            rd_gray <= {PTR_WIDTH{1'b0}};

            empty  <= 1'b1;
            aempty <= 1'b1;

            rd_data <= {DATA_WIDTH{1'b0}};

        end
        else begin

            rd_bin  <= rd_bin_next;
            rd_gray <= rd_gray_next;

            empty  <= empty_next;
            aempty <= aempty_next;

            // FIFO memory read
            if (read_do) begin

                rd_data <= mem[rd_bin[ADDR_WIDTH-1:0]];

            end

        end

    end

    // =========================================================
    // MEMORY WRITE
    //
    // Memory is written only in the write clock domain.
    // =========================================================

    always @(posedge wr_clk) begin

        if (write_do) begin

            mem[wr_bin[ADDR_WIDTH-1:0]] <= wr_data;

        end

    end

endmodule
`timescale 1ns/1ps

module tb_async_fifo;

    // ============================================================
    // PARAMETERS
    // ============================================================

    parameter DATA_WIDTH = 8;
    parameter DEPTH      = 16;
    parameter ADDR_WIDTH = 4;
    parameter PTR_WIDTH  = ADDR_WIDTH + 1;

    // ============================================================
    // CLOCK AND RESET
    // ============================================================

    reg wr_clk;
    reg rd_clk;
    reg arst_n;

    // ============================================================
    // WRITE INTERFACE
    // ============================================================

    reg                  wr_en;
    reg [DATA_WIDTH-1:0] wr_data;

    // ============================================================
    // READ INTERFACE
    // ============================================================

    reg                  rd_en;
    wire [DATA_WIDTH-1:0] rd_data;

    // ============================================================
    // FIFO FLAGS
    // ============================================================

    wire full;
    wire empty;
    wire afull;
    wire aempty;

    // ============================================================
    // PROGRAMMABLE WATERMARK THRESHOLDS
    // ============================================================

    reg [PTR_WIDTH-1:0] afull_threshold;
    reg [PTR_WIDTH-1:0] aempty_threshold;

    // ============================================================
    // DUT
    // ============================================================

    async_fifo #(
        .DATA_WIDTH(DATA_WIDTH),
        .DEPTH(DEPTH)
        ) dut (

        .wr_clk(wr_clk),
        .rd_clk(rd_clk),
        .arst_n(arst_n),

        .wr_en(wr_en),
        .wr_data(wr_data),

        .rd_en(rd_en),
        .rd_data(rd_data),

        .full(full),
        .empty(empty),

        .afull(afull),
        .aempty(aempty),

        .afull_threshold(afull_threshold),
        .aempty_threshold(aempty_threshold)
    );

    // ============================================================
    // CLOCK GENERATION
    // ============================================================

    // Write clock = 10 ns period
    always #5 wr_clk = ~wr_clk;

    // Read clock = 14 ns period
    // Different frequency and phase
    always #7 rd_clk = ~rd_clk;

    // ============================================================
    // TEST COUNTERS
    // ============================================================

    integer errors;
    integer writes;
    integer reads;

    // ============================================================
    // EXPECTED DATA QUEUE
    // ============================================================

    reg [DATA_WIDTH-1:0] expected_queue [0:DEPTH*4-1];

    integer q_write;
    integer q_read;

    // ============================================================
    // WRITE SCOREBOARD
    // ============================================================

    always @(posedge wr_clk) begin

        if (!arst_n) begin

            q_write <= 0;
            writes  <= 0;

        end
        else begin

            if (wr_en && !full) begin

                expected_queue[q_write] <= wr_data;

                q_write <= q_write + 1;

                writes <= writes + 1;

                $display(
                    "[WRITE] time=%0t data=%h full=%b afull=%b",
                    $time,
                    wr_data,
                    full,
                    afull
                );

            end

        end

    end

    // ============================================================
    // READ SCOREBOARD
    // ============================================================

    always @(posedge rd_clk) begin

        if (!arst_n) begin

            q_read <= 0;
            reads  <= 0;

        end
        else begin

            if (rd_en && !empty) begin

                #1;

                if (rd_data !== expected_queue[q_read]) begin

                    $display(
                        "[ERROR] time=%0t expected=%h received=%h",
                        $time,
                        expected_queue[q_read],
                        rd_data
                    );

                    errors = errors + 1;

                end
                else begin

                    $display(
                        "[READ PASS] time=%0t data=%h empty=%b aempty=%b",
                        $time,
                        rd_data,
                        empty,
                        aempty
                    );

                end

                q_read <= q_read + 1;

                reads <= reads + 1;

            end

        end

    end

    // ============================================================
    // RESET TASK
    // ============================================================

    task reset_fifo;

        begin

            $display("");
            $display("==============================================");
            $display("RESET TEST");
            $display("==============================================");

            arst_n = 0;

            wr_en  = 0;
            rd_en  = 0;

            wr_data = 0;

            #40;

            arst_n = 1;

            #30;

            $display(
                "[RESET COMPLETE] full=%b empty=%b afull=%b aempty=%b",
                full,
                empty,
                afull,
                aempty
            );

            if (empty !== 1'b1) begin

                $display("[ERROR] FIFO should be EMPTY after reset");

                errors = errors + 1;

            end
            else begin

                $display("[PASS] FIFO EMPTY after reset");

            end

        end

    endtask

    // ============================================================
    // WRITE ONE DATA
    // ============================================================

    task write_one;

        input [DATA_WIDTH-1:0] data;

        begin

            @(negedge wr_clk);

            if (!full) begin

                wr_en   = 1;
                wr_data = data;

                @(negedge wr_clk);

                wr_en = 0;

            end
            else begin

                $display(
                    "[INFO] Write blocked because FIFO is FULL"
                );

            end

        end

    endtask

    // ============================================================
    // READ ONE DATA
    // ============================================================

    task read_one;

        begin

            @(negedge rd_clk);

            if (!empty) begin

                rd_en = 1;

                @(negedge rd_clk);

                rd_en = 0;

            end
            else begin

                $display(
                    "[INFO] Read blocked because FIFO is EMPTY"
                );

            end

        end

    endtask

    // ============================================================
    // TEST 1
    // NORMAL WRITE / READ
    // ============================================================

    task normal_test;

        integer i;

        begin

            $display("");
            $display("==============================================");
            $display("TEST 1 : NORMAL WRITE / READ");
            $display("==============================================");

            for (i = 0; i < 8; i = i + 1) begin

                write_one(8'hA0 + i);

            end

            #100;

            for (i = 0; i < 8; i = i + 1) begin

                read_one();

            end

            #150;

        end

    endtask

    // ============================================================
    // TEST 2
    // FILL FIFO COMPLETELY
    // ============================================================

    task full_test;

        integer i;

        begin

            $display("");
            $display("==============================================");
            $display("TEST 2 : FULL BOUNDARY");
            $display("==============================================");

            // Reset before full test

            arst_n = 0;

            #30;

            arst_n = 1;

            #30;

            // Write DEPTH entries

            for (i = 0; i < DEPTH; i = i + 1) begin

                write_one(8'h10 + i);

            end

            // Allow pointer synchronization

            #150;

            $display(
                "[FULL CHECK] full=%b afull=%b",
                full,
                afull
            );

            if (full === 1'b1) begin

                $display("[PASS] FIFO FULL flag asserted");

            end
            else begin

                $display("[ERROR] FIFO FULL flag NOT asserted");

                errors = errors + 1;

            end

            // Try one additional write

            $display("[FULL TEST] Attempting write while FULL");

            write_one(8'hFF);

            #50;

        end

    endtask

    // ============================================================
    // TEST 3
    // EMPTY BOUNDARY
    // ============================================================

    task empty_test;

        integer i;

        begin

            $display("");
            $display("==============================================");
            $display("TEST 3 : EMPTY BOUNDARY");
            $display("==============================================");

            // Read all existing data

            for (i = 0; i < DEPTH; i = i + 1) begin

                read_one();

            end

            #150;

            $display(
                "[EMPTY CHECK] empty=%b aempty=%b",
                empty,
                aempty
            );

            if (empty === 1'b1) begin

                $display("[PASS] FIFO EMPTY flag asserted");

            end
            else begin

                $display("[ERROR] FIFO EMPTY flag NOT asserted");

                errors = errors + 1;

            end

            // Attempt read while empty

            $display("[EMPTY TEST] Attempting read while EMPTY");

            read_one();

            #50;

        end

    endtask

    // ============================================================
    // TEST 4
    // AFULL WATERMARK
    // ============================================================

    task afull_test;

        integer i;

        begin

            $display("");
            $display("==============================================");
            $display("TEST 4 : AFULL WATERMARK");
            $display("==============================================");

            // Reset

            arst_n = 0;

            #30;

            arst_n = 1;

            #30;

            // AFULL when FIFO reaches 12 entries

            afull_threshold = 12;

            aempty_threshold = 2;

            $display(
                "[CONFIG] AFULL_THRESHOLD=%0d",
                afull_threshold
            );

            // Write 12 entries

            for (i = 0; i < 12; i = i + 1) begin

                write_one(8'h50 + i);

            end

            #150;

            $display(
                "[AFULL CHECK] afull=%b",
                afull
            );

            if (afull === 1'b1) begin

                $display("[PASS] AFULL asserted at threshold");

            end
            else begin

                $display("[ERROR] AFULL not asserted");

                errors = errors + 1;

            end

        end

    endtask

    // ============================================================
    // TEST 5
    // AEMPTY WATERMARK
    // ============================================================

    task aempty_test;

        integer i;

        begin

            $display("");
            $display("==============================================");
            $display("TEST 5 : AEMPTY WATERMARK");
            $display("==============================================");

            // Read until only 2 entries remain

            for (i = 0; i < 10; i = i + 1) begin

                read_one();

            end

            #150;

            $display(
                "[AEMPTY CHECK] aempty=%b",
                aempty
            );

            if (aempty === 1'b1) begin

                $display("[PASS] AEMPTY asserted");

            end
            else begin

                $display("[ERROR] AEMPTY not asserted");

                errors = errors + 1;

            end

        end

    endtask

    // ============================================================
    // MAIN TEST
    // ============================================================

    initial begin

        // Initial values

        wr_clk = 0;
        rd_clk = 0;

        arst_n = 0;

        wr_en = 0;
        rd_en = 0;

        wr_data = 0;

        afull_threshold = 12;
        aempty_threshold = 2;

        errors = 0;
        writes = 0;
        reads = 0;

        q_write = 0;
        q_read = 0;

        // Reset

        reset_fifo();

        // Test 1

        normal_test();

        // Test 2

        full_test();

        // Test 3

        empty_test();

        // Test 4

        afull_test();

        // Test 5

        aempty_test();

        // Allow final operations

        #300;

        // ========================================================
        // FINAL RESULT
        // ========================================================

        $display("");
        $display("==============================================");
        $display("        PS-04 ASYNC FIFO FINAL RESULT");
        $display("==============================================");

        $display("Total writes = %0d", writes);
        $display("Total reads  = %0d", reads);
        $display("Total errors = %0d", errors);

        if (errors == 0) begin

            $display("");
            $display("**************************************");
            $display("       ALL TESTS PASSED");
            $display("**************************************");
            $display("");

        end
        else begin

            $display("");
            $display("**************************************");
            $display("       TEST FAILED");
            $display("       Errors = %0d", errors);
            $display("**************************************");
            $display("");

        end

        $finish;

    end

    // ============================================================
    // VCD WAVEFORM
    // ============================================================

    initial begin

        $dumpfile("async_fifo.vcd");

        $dumpvars(0, tb_async_fifo);

    end

endmodule

src/async_fifo.vcd
$date
	Fri Aug 28 10:32:34 2026
$end
$version
	Icarus Verilog
$end
$timescale
	1ps
$end
$scope module tb_async_fifo $end
$var wire 8 ! rd_data [7:0] $end
$var wire 1 " full $end
$var wire 1 # empty $end
$var wire 1 $ afull $end
$var wire 1 % aempty $end
$var parameter 32 & ADDR_WIDTH $end
$var parameter 32 ' DATA_WIDTH $end
$var parameter 32 ( DEPTH $end
$var parameter 33 ) PTR_WIDTH $end
$var reg 5 * aempty_threshold [4:0] $end
$var reg 5 + afull_threshold [4:0] $end
$var reg 1 , arst_n $end
$var reg 1 - rd_clk $end
$var reg 1 . rd_en $end
$var reg 1 / wr_clk $end
$var reg 8 0 wr_data [7:0] $end
$var reg 1 1 wr_en $end
$var integer 32 2 errors [31:0] $end
$var integer 32 3 q_read [31:0] $end
$var integer 32 4 q_write [31:0] $end
$var integer 32 5 reads [31:0] $end
$var integer 32 6 writes [31:0] $end
$scope module dut $end
$var wire 5 7 aempty_threshold [4:0] $end
$var wire 5 8 afull_threshold [4:0] $end
$var wire 1 , arst_n $end
$var wire 1 - rd_clk $end
$var wire 1 . rd_en $end
$var wire 1 9 read_do $end
$var wire 1 / wr_clk $end
$var wire 8 : wr_data [7:0] $end
$var wire 1 1 wr_en $end
$var wire 1 ; write_do $end
$var wire 5 < write_count [4:0] $end
$var wire 5 = wr_bin_sync [4:0] $end
$var wire 5 > read_count [4:0] $end
$var wire 5 ? rd_bin_sync [4:0] $end
$var wire 1 @ full_next $end
$var wire 5 A full_compare [4:0] $end
$var wire 1 B empty_next $end
$var wire 1 C afull_next $end
$var wire 1 D aempty_next $end
$var parameter 32 E ADDR_WIDTH $end
$var parameter 32 F DATA_WIDTH $end
$var parameter 32 G DEPTH $end
$var parameter 33 H PTR_WIDTH $end
$var reg 1 % aempty $end
$var reg 1 $ afull $end
$var reg 1 # empty $end
$var reg 1 " full $end
$var reg 5 I rd_bin [4:0] $end
$var reg 5 J rd_bin_next [4:0] $end
$var reg 8 K rd_data [7:0] $end
$var reg 5 L rd_gray [4:0] $end
$var reg 5 M rd_gray_next [4:0] $end
$var reg 5 N rd_gray_sync1 [4:0] $end
$var reg 5 O rd_gray_sync2 [4:0] $end
$var reg 5 P wr_bin [4:0] $end
$var reg 5 Q wr_bin_next [4:0] $end
$var reg 5 R wr_gray [4:0] $end
$var reg 5 S wr_gray_next [4:0] $end
$var reg 5 T wr_gray_sync1 [4:0] $end
$var reg 5 U wr_gray_sync2 [4:0] $end
$scope function gray_to_binary $end
$var reg 5 V gray [4:0] $end
$var integer 32 W i [31:0] $end
$upscope $end
$upscope $end
$scope task aempty_test $end
$var integer 32 X i [31:0] $end
$upscope $end
$scope task afull_test $end
$var integer 32 Y i [31:0] $end
$upscope $end
$scope task empty_test $end
$var integer 32 Z i [31:0] $end
$upscope $end
$scope task full_test $end
$var integer 32 [ i [31:0] $end
$upscope $end
$scope task normal_test $end
$var integer 32 \ i [31:0] $end
$upscope $end
$scope task read_one $end
$upscope $end
$scope task reset_fifo $end
$upscope $end
$scope task write_one $end
$var reg 8 ] data [7:0] $end
$upscope $end
$upscope $end
$enddefinitions $end
$comment Show the parameter values. $end
$dumpall
b101 H
b10000 G
b1000 F
b100 E
b101 )
b10000 (
b1000 '
b100 &
$end
#0
$dumpvars
bx ]
bx \
bx [
bx Z
bx Y
bx X
b11111111111111111111111111111111 W
b0 V
b0 U
b0 T
b0 S
b0 R
b0 Q
b0 P
b0 O
b0 N
b0 M
b0 L
b0 K
b0 J
b0 I
1D
0C
1B
b11000 A
0@
b0 ?
b0 >
b0 =
b0 <
0;
b0 :
09
b1100 8
b10 7
b0 6
b0 5
b0 4
b0 3
b0 2
01
b0 0
0/
0.
0-
0,
b1100 +
b10 *
1%
0$
1#
0"
b0 !
$end
#5000
1/
#7000
1-
#10000
0/
#14000
0-
#15000
1/
#20000
0/
#21000
1-
#25000
1/
#28000
0-
#30000
0/
#35000
1/
1-
#40000
0/
1,
#42000
0-
#45000
1/
#49000
1-
#50000
0/
#55000
1/
#56000
0-
#60000
0/
#63000
1-
#65000
1/
#70000
b1 S
b1 Q
1;
b10100000 0
b10100000 :
11
0/
0-
b10100000 ]
b0 \
#75000
b11 S
b10 Q
b1 6
b1 4
b1 R
b1 <
b1 P
1/
#77000
b1 T
1-
#80000
b1 S
b1 Q
0;
b10100001 ]
b1 \
01
0/
#84000
0-
#85000
1/
#90000
b11 S
b10 Q
1;
b10100001 0
b10100001 :
11
0/
#91000
b1 >
b1 =
b11111111111111111111111111111111 W
b1 V
0B
b1 U
1-
#95000
b10 S
b11 Q
b10 6
b10 4
b11 R
b10 <
b10 P
1/
#98000
0-
#100000
b11 S
b10 Q
0;
b10100010 ]
b10 \
01
0/
#105000
b11 T
0#
1/
1-
#110000
b10 S
b11 Q
1;
b10100010 0
b10100010 :
11
0/
#112000
0-
#115000
b110 S
b100 Q
b11 6
b11 4
b10 R
b11 <
b11 P
1/
#119000
b10 >
b10 =
b11111111111111111111111111111111 W
b11 V
b11 U
b10 T
1-
#120000
b10 S
b11 Q
0;
b10100011 ]
b11 \
01
0/
#125000
1/
#126000
0-
#130000
b110 S
b100 Q
1;
b10100011 0
b10100011 :
11
0/
#133000
0D
b11 >
b11 =
b11111111111111111111111111111111 W
b10 V
b10 U
1-
#135000
b111 S
b101 Q
b100 6
b100 4
b110 R
b100 <
b100 P
1/
#140000
b110 S
b100 Q
0;
b10100100 ]
b100 \
01
0/
0-
#145000
1/
#147000
0%
b110 T
1-
#150000
b111 S
b101 Q
1;
b10100100 0
b10100100 :
11
0/
#154000
0-
#155000
b101 S
b110 Q
b101 6
b101 4
b111 R
b101 <
b101 P
1/
#160000
b111 S
b101 Q
0;
b10100101 ]
b101 \
01
0/
#161000
b100 >
b100 =
b11111111111111111111111111111111 W
b110 V
b110 U
b111 T
1-
#165000
1/
#168000
0-
#170000
b101 S
b110 Q
1;
b10100101 0
b10100101 :
11
0/
#175000
b100 S
b111 Q
b101 >
b101 =
b11111111111111111111111111111111 W
b111 V
b110 6
b110 4
b101 R
b110 <
b110 P
b111 U
1/
1-
#180000
b101 S
b110 Q
0;
b10100110 ]
b110 \
01
0/
#182000
0-
#185000
1/
#189000
b101 T
1-
#190000
b100 S
b111 Q
1;
b10100110 0
b10100110 :
11
0/
#195000
b1100 S
b1000 Q
b111 6
b111 4
b100 R
b111 <
b111 P
1/
#196000
0-
#200000
b100 S
b111 Q
0;
b10100111 ]
b111 \
01
0/
#203000
b110 >
b110 =
b11111111111111111111111111111111 W
b101 V
b101 U
b100 T
1-
#205000
1/
#210000
b1100 S
b1000 Q
1;
b10100111 0
b10100111 :
11
0/
0-
#215000
b1101 S
b1001 Q
b1000 6
b1000 4
b1100 R
b1000 <
b1000 P
1/
#217000
b111 >
b111 =
b11111111111111111111111111111111 W
b100 V
b100 U
b1100 T
1-
#220000
b1100 S
b1000 Q
0;
b1000 \
01
0/
#224000
0-
#225000
1/
#230000
0/
#231000
b1000 >
b1000 =
b11111111111111111111111111111111 W
b1100 V
b1100 U
1-
#235000
1/
#238000
0-
#240000
0/
#245000
1/
1-
#250000
0/
#252000
0-
#255000
1/
#259000
1-
#260000
0/
#265000
1/
#266000
0-
#270000
0/
#273000
1-
#275000
1/
#280000
0/
0-
#285000
1/
#287000
1-
#290000
0/
#294000
0-
#295000
1/
#300000
0/
#301000
1-
#305000
1/
#308000
0-
#310000
0/
#315000
1/
1-
#320000
0/
b0 \
#322000
b1 M
b1 J
19
1.
0-
#325000
1/
#329000
b11 M
b10 J
b10100000 !
b10100000 K
b1 L
b111 >
b1 I
1-
#330000
b1 5
b1 3
0/
#335000
b1 N
1/
#336000
b1 M
b1 J
09
b1 \
0.
0-
#340000
0/
#343000
1-
#345000
b111 <
b1 ?
b11111111111111111111111111111111 W
b1 V
b11001 A
b1 O
1/
#350000
b11 M
b10 J
19
1.
0/
0-
#355000
1/
#357000
b10 M
b11 J
b10100001 !
b10100001 K
b11 L
b110 >
b10 I
1-
#358000
b10 5
b10 3
#360000
0/
#364000
b11 M
b10 J
09
b10 \
0.
0-
#365000
b11 N
1/
#370000
0/
#371000
1-
#375000
b110 <
b10 ?
b11111111111111111111111111111111 W
b11 V
b11011 A
b11 O
1/
#378000
b10 M
b11 J
19
1.
0-
#380000
0/
#385000
b110 M
b100 J
b10100010 !
b10100010 K
b10 L
b101 >
b11 I
1/
1-
#386000
b11 5
b11 3
#390000
0/
#392000
b10 M
b11 J
09
b11 \
0.
0-
#395000
b10 N
1/
#399000
1-
#400000
0/
#405000
b101 <
b11 ?
b11111111111111111111111111111111 W
b10 V
b11010 A
b10 O
1/
#406000
b110 M
b100 J
19
1.
0-
#410000
0/
#413000
b111 M
b101 J
b10100011 !
b10100011 K
b110 L
b100 >
b100 I
1-
#414000
b100 5
b100 3
#415000
b110 N
1/
#420000
b110 M
b100 J
09
b100 \
0.
0/
0-
#425000
b100 <
b100 ?
b11111111111111111111111111111111 W
b110 V
b11110 A
b110 O
1/
#427000
1-
#430000
0/
#434000
b111 M
b101 J
19
1.
0-
#435000
1/
#440000
0/
#441000
b101 M
b110 J
b10100100 !
b10100100 K
b111 L
b11 >
b101 I
1-
#442000
b101 5
b101 3
#445000
b111 N
1/
#448000
b111 M
b101 J
09
b101 \
0.
0-
#450000
0/
#455000
b11 <
b101 ?
b11111111111111111111111111111111 W
b111 V
b11111 A
b111 O
1/
1-
#460000
0/
#462000
b101 M
b110 J
19
1.
0-
#465000
1/
#469000
b100 M
b111 J
b10100101 !
b10100101 K
b101 L
1D
b10 >
b110 I
1-
#470000
b110 5
b110 3
0/
#475000
b101 N
1/
#476000
b101 M
b110 J
09
b110 \
0.
0-
#480000
0/
#483000
1%
1-
#485000
b10 <
b110 ?
b11111111111111111111111111111111 W
b101 V
b11101 A
b101 O
1/
#490000
b100 M
b111 J
19
1.
0/
0-
#495000
1/
#497000
1B
b1100 M
b1000 J
b10100110 !
b10100110 K
b100 L
b1 >
b111 I
1-
#498000
b111 5
b111 3
#500000
0/
#504000
0B
b100 M
b111 J
09
b111 \
0.
0-
#505000
b100 N
1/
#510000
0/
#511000
1-
#515000
b1 <
b111 ?
b11111111111111111111111111111111 W
b100 V
b11100 A
b100 O
1/
#518000
1B
b1100 M
b1000 J
19
1.
0-
#520000
0/
#525000
09
1B
b1100 M
b1000 J
b10100111 !
b10100111 K
1#
b1100 L
b0 >
b1000 I
1/
1-
#526000
b1000 5
b1000 3
#530000
0/
#532000
b1000 \
0.
0-
#535000
b1100 N
1/
#539000
1-
#540000
0/
#545000
b10100 A
b0 <
b1000 ?
b11111111111111111111111111111111 W
b1100 V
b1100 O
1/
